skilz/__init__.py
skilz/__main__.py
skilz/agent_registry.py
skilz/agents.py
skilz/api_client.py
skilz/cli.py
skilz/completion.py
skilz/config.py
skilz/config_sync.py
skilz/errors.py
skilz/git_install.py
skilz/git_ops.py
skilz/installer.py
skilz/link_ops.py
skilz/manifest.py
skilz/registry.py
skilz/scanner.py
skilz/commands/__init__.py
skilz/commands/config_cmd.py
skilz/commands/install_cmd.py
skilz/commands/list_cmd.py
skilz/commands/read_cmd.py
skilz/commands/remove_cmd.py
skilz/commands/search_cmd.py
skilz/commands/update_cmd.py
skilz/commands/visit_cmd.py
skilz/data/LOAD_SKILLS.md
skilz-1.10.0.dist-info/METADATA
skilz-1.10.0.dist-info/WHEEL
skilz-1.10.0.dist-info/entry_points.txt
skilz-1.10.0.dist-info/RECORD
