Metadata-Version: 2.4
Name: skilz
Version: 1.10.0
Summary: The universal package manager for AI skills
Project-URL: Homepage, https://github.com/spillwave/skilz-cli
Project-URL: Documentation, https://skillzwave.ai
Project-URL: Repository, https://github.com/spillwave/skilz-cli
Author-email: Spillwave <contact@spillwave.com>
License-Expression: MIT
Keywords: ai,claude,opencode,package-manager,skills
Classifier: Development Status :: 3 - Alpha
Classifier: Environment :: Console
Classifier: Intended Audience :: Developers
Classifier: License :: OSI Approved :: MIT License
Classifier: Operating System :: OS Independent
Classifier: Programming Language :: Python :: 3
Classifier: Programming Language :: Python :: 3.10
Classifier: Programming Language :: Python :: 3.11
Classifier: Programming Language :: Python :: 3.12
Classifier: Topic :: Software Development :: Libraries :: Python Modules
Requires-Python: >=3.10
Requires-Dist: pyyaml>=6.0
Provides-Extra: dev
Requires-Dist: mypy>=1.0; extra == 'dev'
Requires-Dist: pytest-cov>=4.0; extra == 'dev'
Requires-Dist: pytest>=7.0; extra == 'dev'
Requires-Dist: ruff>=0.1.0; extra == 'dev'
